{
	"id": "5b1cb95e-5e5d-4fed-b71f-a3016b78dbdb",
	"name": "vRealize Automation Cloud",
	"values": [
		{
			"key": "url-home",
			"value": "https://api.mgmt.cloud.vmware.com",
			"enabled": true
		},
		{
			"key": "refreshToken",
			"value": "",
			"enabled": true
		},
		{
			"key": "token",
			"value": "",
			"enabled": true
		},
		{
			"key": "projectId",
			"value": "",
			"enabled": true
		},
		{
			"key": "projectLink",
			"value": "",
			"enabled": true
		},
		{
			"key": "deploymentId",
			"value": "",
			"enabled": true
		},
		{
			"key": "resourceLink",
			"value": "",
			"enabled": true
		}
	],
	"_postman_variable_scope": "environment",
	"_postman_exported_at": "2019-09-17T17:25:51.432Z",
	"_postman_exported_using": "Postman/7.7.0"
}